logcraft/__init__.py
logcraft/macro.py
logcraft-0.0.1.post1.dist-info/LICENSE
logcraft-0.0.1.post1.dist-info/METADATA
logcraft-0.0.1.post1.dist-info/WHEEL
logcraft-0.0.1.post1.dist-info/top_level.txt
logcraft-0.0.1.post1.dist-info/RECORD
