Metadata-Version: 2.1
Name: logcraft
Version: 0.0.1.post1
Summary: Python Macro-Generated Logging from Comments
Home-page: https://github.com/ryanlyn/logcraft
Author: Ryan Lyn
Author-email: 
License: MIT License
Keywords: logging,macro
Platform: any
Classifier: Development Status :: 3 - Alpha
Classifier: Intended Audience :: Developers
Classifier: Operating System :: OS Independent
Classifier: Programming Language :: Python
Classifier: Programming Language :: Python :: 3.6
Classifier: Programming Language :: Python :: 3.7
Classifier: Programming Language :: Python :: 3.8
Classifier: Programming Language :: Python :: Implementation :: CPython
Classifier: Topic :: Software Development :: Libraries
Classifier: Topic :: Software Development :: Libraries :: Python Modules
Classifier: Topic :: System :: Logging
Classifier: License :: OSI Approved :: MIT License
